tracardi_url_parser/plugin.py
tracardi_url_parser/model/configuration.py
tracardi_url_parser/model/__pycache__/configuration.cpython-38.pyc
tracardi_url_parser/test/unit/test_url_plugin.py
tracardi_url_parser-0.6.0.dist-info/LICENSE.md
tracardi_url_parser-0.6.0.dist-info/METADATA
tracardi_url_parser-0.6.0.dist-info/WHEEL
tracardi_url_parser-0.6.0.dist-info/top_level.txt
tracardi_url_parser-0.6.0.dist-info/RECORD
